Workbook

Sheet About
A1: V4-M2 golden workings: the profit of a synthetic CT period adjusted for tax (DEC-099)
A3: V4-M2 (DEC-099) golden: one synthetic 12-month CT period. Each journal's other side is the directors' loan account (2230); the rules and manual adjustments are synthetic test fixtures, not tax advice. Worked by hand in docs/architecture/v4-m2-golden-workings.xlsx.
A4: CT period: 2027-01-01 to 2027-12-31.
A5: Accounting profit = the net credit of income and expense accounts in the period, leaving out the tax charge (7100) and journals outside the period.
A6: A rule adds back (debits - credits) x percentage of its account for the journals inside both the period and the rule's dates; a credit result is deducted.
A7: Manual adjustments count unless withdrawn. Green cells are the golden the API test asserts.

Sheet Journals
A1: Date | B1: Description | C1: Account | D1: Kind | E1: Debit | F1: Credit | G1: In period | H1: Net credit to profit
A2: 46387 | B2: Sundry cost before the period | C2: 8000 | D2: EXPENSE | E2: 100 | F2: 0 | G2: =AND(A2>=DATE(2027,1,1),A2<=DATE(2027,12,31)) | H2: =IF(AND(G2,D2<>"TAX"),F2-E2,0)
A3: 46419 | B3: Professional fees before the rule's start | C3: 6600 | D3: EXPENSE | E3: 1000 | F3: 0 | G3: =AND(A3>=DATE(2027,1,1),A3<=DATE(2027,12,31)) | H3: =IF(AND(G3,D3<>"TAX"),F3-E3,0)
A4: 46477 | B4: Sales | C4: 4000 | D4: INCOME | E4: 0 | F4: 50000 | G4: =AND(A4>=DATE(2027,1,1),A4<=DATE(2027,12,31)) | H4: =IF(AND(G4,D4<>"TAX"),F4-E4,0)
A5: 46492 | B5: Client entertaining | C5: 8000 | D5: EXPENSE | E5: 1234.57 | F5: 0 | G5: =AND(A5>=DATE(2027,1,1),A5<=DATE(2027,12,31)) | H5: =IF(AND(G5,D5<>"TAX"),F5-E5,0)
A6: 46568 | B6: A grant treated as not taxable | C6: 4100 | D6: INCOME | E6: 0 | F6: 800 | G6: =AND(A6>=DATE(2027,1,1),A6<=DATE(2027,12,31)) | H6: =IF(AND(G6,D6<>"TAX"),F6-E6,0)
A7: 46660 | B7: Professional fees, part capital | C7: 6600 | D7: EXPENSE | E7: 2000 | F7: 0 | G7: =AND(A7>=DATE(2027,1,1),A7<=DATE(2027,12,31)) | H7: =IF(AND(G7,D7<>"TAX"),F7-E7,0)
A8: 46721 | B8: Wages | C8: 6000 | D8: EXPENSE | E8: 20000 | F8: 0 | G8: =AND(A8>=DATE(2027,1,1),A8<=DATE(2027,12,31)) | H8: =IF(AND(G8,D8<>"TAX"),F8-E8,0)
A9: 46752 | B9: Depreciation | C9: 6900 | D9: EXPENSE | E9: 3000 | F9: 0 | G9: =AND(A9>=DATE(2027,1,1),A9<=DATE(2027,12,31)) | H9: =IF(AND(G9,D9<>"TAX"),F9-E9,0)
A10: 46752 | B10: Corporation tax charge | C10: 7100 | D10: TAX | E10: 9000 | F10: 0 | G10: =AND(A10>=DATE(2027,1,1),A10<=DATE(2027,12,31)) | H10: =IF(AND(G10,D10<>"TAX"),F10-E10,0)
G11: Accounting profit | H11: =ROUND(SUM(H2:H10),2)

Sheet Adjustments
A1: Source | B1: Account | C1: Category | D1: Percentage | E1: From | F1: Debits in range | G1: Credits in range | H1: Adjustment (+ add, - deduct) | I1: Expected | J1: Direction
A2: RULE | B2: 8000 | C2: ENTERTAINING | D2: 100 | E2: 46388 | F2: =SUMIFS(Journals!$E$2:$E$10,Journals!$C$2:$C$10,"8000",Journals!$A$2:$A$10,">="&E2,Journals!$A$2:$A$10,"<="&DATE(2027,12,31)) | G2: =SUMIFS(Journals!$F$2:$F$10,Journals!$C$2:$C$10,"8000",Journals!$A$2:$A$10,">="&E2,Journals!$A$2:$A$10,"<="&DATE(2027,12,31)) | H2: =ROUND((F2-G2)*D2/100,2) | I2: 1234.57 | J2: ADD
A3: RULE | B3: 6900 | C3: DEPRECIATION | D3: 100 | E3: 46388 | F3: =SUMIFS(Journals!$E$2:$E$10,Journals!$C$2:$C$10,"6900",Journals!$A$2:$A$10,">="&E3,Journals!$A$2:$A$10,"<="&DATE(2027,12,31)) | G3: =SUMIFS(Journals!$F$2:$F$10,Journals!$C$2:$C$10,"6900",Journals!$A$2:$A$10,">="&E3,Journals!$A$2:$A$10,"<="&DATE(2027,12,31)) | H3: =ROUND((F3-G3)*D3/100,2) | I3: 3000 | J3: ADD
A4: RULE | B4: 4100 | C4: NON_TAXABLE_INCOME | D4: 100 | E4: 46388 | F4: =SUMIFS(Journals!$E$2:$E$10,Journals!$C$2:$C$10,"4100",Journals!$A$2:$A$10,">="&E4,Journals!$A$2:$A$10,"<="&DATE(2027,12,31)) | G4: =SUMIFS(Journals!$F$2:$F$10,Journals!$C$2:$C$10,"4100",Journals!$A$2:$A$10,">="&E4,Journals!$A$2:$A$10,"<="&DATE(2027,12,31)) | H4: =ROUND((F4-G4)*D4/100,2) | I4: -800 | J4: DEDUCT
A5: RULE | B5: 6600 | C5: LEGAL_PROFESSIONAL | D5: 25 | E5: 46569 | F5: =SUMIFS(Journals!$E$2:$E$10,Journals!$C$2:$C$10,"6600",Journals!$A$2:$A$10,">="&E5,Journals!$A$2:$A$10,"<="&DATE(2027,12,31)) | G5: =SUMIFS(Journals!$F$2:$F$10,Journals!$C$2:$C$10,"6600",Journals!$A$2:$A$10,">="&E5,Journals!$A$2:$A$10,"<="&DATE(2027,12,31)) | H5: =ROUND((F5-G5)*D5/100,2) | I5: 500 | J5: ADD
A6: MANUAL | C6: OTHER | H6: 350 | I6: 350 | J6: ADD
A7: MANUAL | C7: OTHER | H7: 0 | I7: 0 | J7: DEDUCT (withdrawn: not counted)

Sheet Statement
A1: Line | B1: Workings | C1: Expected (API)
A2: Accounting profit | B2: =Journals!H11 | C2: 23565.43
A3: Total added | B3: =SUMIF(Adjustments!H2:H7,">0") | C3: 5084.57
A4: Total deducted | B4: =-SUMIF(Adjustments!H2:H7,"<0") | C4: 800
A5: Adjusted profit (before capital allowances and losses) | B5: =B2+B3-B4 | C5: 27850
A7: Check: workings equal expected | B7: =AND(ROUND(B2-C2,2)=0,ROUND(B3-C3,2)=0,ROUND(B4-C4,2)=0,ROUND(B5-C5,2)=0)
