Workbook

Sheet About
A1: V4-M3 golden workings: capital allowances of two synthetic CT periods (DEC-100)
A3: V4-M3 (DEC-100) golden: two consecutive synthetic CT periods (2027, 12 months; then 1 January to 30 June 2028, 182 days). The rates and limits are entered as test fixtures and verified by a second person in the test; they are not tax advice. Worked by hand in docs/architecture/v4-m3-golden-workings.xlsx.
A4: Fraction: 1 for a 12-month period, else days / 365. AIA: the limit x fraction, given to AIA additions in date order; the excess goes into the main pool.
A5: Disposal value: the lower of the proceeds and the cost. Pool: opening + additions - disposal values = available.
A6: Below zero: balancing charge. A single asset pool disposed of: balancing allowance. Main or special pool at or under the small pools limit x fraction: all claimed.
A7: Otherwise WDA = available x rate x fraction, rounded to the penny. Green cells are the golden the tests assert; the Check rows must be TRUE.

Sheet Rules
A1: Rule | B1: Value
A2: AIA annual limit | B2: 1000000
A3: Main rate % | B3: 18
A4: Special rate % | B4: 6
A5: Small pools limit | B5: 1000

Sheet Assets
A1: Key | B1: Description | C1: Category | D1: Acquired | E1: Cost | F1: Disposed | G1: Proceeds | H1: Disposal value
A2: S0 | B2: Old machine in its own pool | C2: SINGLE_ASSET_POOL | D2: 45717 | E2: 5000 | F2: 46600 | G2: 1000 | H2: =MIN(G2,E2)
A3: D1 | B3: Old van in the main pool | C3: MAIN_POOL | D3: 45809 | E3: 2500 | F3: 46631 | G3: 3000 | H3: =MIN(G3,E3)
A4: A1 | B4: Production line | C4: AIA | D4: 46419 | E4: 900000
A5: A3 | B5: Office furniture | C5: MAIN_POOL | D5: 46447 | E5: 5000 | F5: 46874 | G5: 6000 | H5: =MIN(G5,E5)
A6: A6 | B6: Artwork (not plant) | C6: NOT_QUALIFYING | D6: 46478 | E6: 10000
A7: A2 | B7: Packing machine | C7: AIA | D7: 46508 | E7: 300000
A8: A4 | B8: Integral features | C8: SPECIAL_RATE_POOL | D8: 46539 | E8: 30000 | F8: 46844 | G8: 40000 | H8: =MIN(G8,E8)
A9: A5 | B9: Short-life computer | C9: SINGLE_ASSET_POOL | D9: 46569 | E9: 4000 | F9: 46905 | G9: 3500 | H9: =MIN(G9,E9)
A10: A7 | B10: Robot cell | C10: AIA | D10: 46813 | E10: 600000

Sheet Period 1
A1: CT period 2027-01-01 to 2027-12-31
A2: Days | B2: =DATE(2027,12,31)-DATE(2027,1,1)+1
A3: Fraction | B3: =1
A4: AIA available | B4: =ROUND(Rules!$B$2*B3,2) | C4: 1000000
A5: Small pools limit | B5: =ROUND(Rules!$B$5*B3,2)
A7: AIA addition | B7: Cost | C7: AIA | D7: To main pool | E7: Expected AIA | F7: Expected to main
A8: A1 Production line | B8: =Assets!$E$4 | C8: =MIN(B8,$B$4) | D8: =B8-C8 | E8: 900000 | F8: 0
A9: A2 Packing machine | B9: =Assets!$E$7 | C9: =MIN(B9,$B$4-SUM(C$8:C8)) | D9: =B9-C9 | E9: 100000 | F9: 200000
A11: Pool | B11: Opening | C11: Additions | D11: Disposal values | E11: Available | F11: WDA (incl. small pool) | G11: Balancing allowance | H11: Balancing charge | I11: Closing | J11: Exp. WDA | K11: Exp. BA | L11: Exp. BC | M11: Exp. closing
A12: MAIN | B12: 10000 | C12: =Assets!$E$5+SUM(D8:D9) | D12: =Assets!$H$3 | E12: =B12+C12-D12 | F12: =IF(E12<0,0,IF(AND(E12>0,E12<=$B$5),E12,ROUND(E12*Rules!$B$3/100*$B$3,2))) | G12: =IF(AND(FALSE,E12>=0),E12,0) | H12: =IF(E12<0,-E12,0) | I12: =IF(E12<0,0,E12-F12-G12) | J12: 38250 | K12: 0 | L12: 0 | M12: 174250
A13: SPECIAL_RATE | B13: 2000 | C13: =Assets!$E$8 | D13: =0 | E13: =B13+C13-D13 | F13: =IF(E13<0,0,IF(AND(E13>0,E13<=$B$5),E13,ROUND(E13*Rules!$B$4/100*$B$3,2))) | G13: =IF(AND(FALSE,E13>=0),E13,0) | H13: =IF(E13<0,-E13,0) | I13: =IF(E13<0,0,E13-F13-G13) | J13: 1920 | K13: 0 | L13: 0 | M13: 30080
A14: SINGLE_ASSET A5 | B14: 0 | C14: =Assets!$E$9 | D14: =0 | E14: =B14+C14-D14 | F14: =IF(OR(E14<0,FALSE),0,ROUND(E14*Rules!$B$3/100*$B$3,2)) | G14: =IF(AND(FALSE,E14>=0),E14,0) | H14: =IF(E14<0,-E14,0) | I14: =IF(E14<0,0,E14-F14-G14) | J14: 720 | K14: 0 | L14: 0 | M14: 3280
A15: SINGLE_ASSET S0 | B15: 3000 | C15: =0 | D15: =Assets!$H$2 | E15: =B15+C15-D15 | F15: =IF(OR(E15<0,TRUE),0,ROUND(E15*Rules!$B$3/100*$B$3,2)) | G15: =IF(AND(TRUE,E15>=0),E15,0) | H15: =IF(E15<0,-E15,0) | I15: =IF(E15<0,0,E15-F15-G15) | J15: 0 | K15: 2000 | L15: 0 | M15: 0
A17: Totals | B17: Workings | C17: Expected
A18: AIA | B18: =SUM(C8:C9) | C18: 1000000
A19: Writing-down allowances | B19: =SUM(F12:F15) | C19: 40890
A20: Balancing allowances | B20: =SUM(G12:G15) | C20: 2000
A21: Allowances | B21: =B18+B19+B20 | C21: 1042890
A22: Balancing charges | B22: =SUM(H12:H15) | C22: 0
A24: Check: workings equal expected | B24: =AND(ROUND(B18-C18,2)=0,ROUND(B19-C19,2)=0,ROUND(B20-C20,2)=0,ROUND(B21-C21,2)=0,ROUND(B22-C22,2)=0,ROUND(B4-C4,2)=0,ROUND(C8-E8,2)=0,ROUND(C9-E9,2)=0,ROUND(F12-J12,2)=0,ROUND(G12-K12,2)=0,ROUND(H12-L12,2)=0,ROUND(I12-M12,2)=0,ROUND(F13-J13,2)=0,ROUND(G13-K13,2)=0,ROUND(H13-L13,2)=0,ROUND(I13-M13,2)=0,ROUND(F14-J14,2)=0,ROUND(G14-K14,2)=0,ROUND(H14-L14,2)=0,ROUND(I14-M14,2)=0,ROUND(F15-J15,2)=0,ROUND(G15-K15,2)=0,ROUND(H15-L15,2)=0,ROUND(I15-M15,2)=0)

Sheet Period 2
A1: CT period 2028-01-01 to 2028-06-30
A2: Days | B2: =DATE(2028,6,30)-DATE(2028,1,1)+1
A3: Fraction | B3: =B2/365
A4: AIA available | B4: =ROUND(Rules!$B$2*B3,2) | C4: 498630.14
A5: Small pools limit | B5: =ROUND(Rules!$B$5*B3,2)
A7: AIA addition | B7: Cost | C7: AIA | D7: To main pool | E7: Expected AIA | F7: Expected to main
A8: A7 Robot cell | B8: =Assets!$E$10 | C8: =MIN(B8,$B$4) | D8: =B8-C8 | E8: 498630.14 | F8: 101369.86
A10: Pool | B10: Opening | C10: Additions | D10: Disposal values | E10: Available | F10: WDA (incl. small pool) | G10: Balancing allowance | H10: Balancing charge | I10: Closing | J10: Exp. WDA | K10: Exp. BA | L10: Exp. BC | M10: Exp. closing
A11: MAIN | B11: ='Period 1'!I12 | C11: =SUM(D8:D8) | D11: =Assets!$H$5 | E11: =B11+C11-D11 | F11: =IF(E11<0,0,IF(AND(E11>0,E11<=$B$5),E11,ROUND(E11*Rules!$B$3/100*$B$3,2))) | G11: =IF(AND(FALSE,E11>=0),E11,0) | H11: =IF(E11<0,-E11,0) | I11: =IF(E11<0,0,E11-F11-G11) | J11: 24289.06 | K11: 0 | L11: 0 | M11: 246330.8
A12: SPECIAL_RATE | B12: ='Period 1'!I13 | C12: =0 | D12: =Assets!$H$8 | E12: =B12+C12-D12 | F12: =IF(E12<0,0,IF(AND(E12>0,E12<=$B$5),E12,ROUND(E12*Rules!$B$4/100*$B$3,2))) | G12: =IF(AND(FALSE,E12>=0),E12,0) | H12: =IF(E12<0,-E12,0) | I12: =IF(E12<0,0,E12-F12-G12) | J12: 80 | K12: 0 | L12: 0 | M12: 0
A13: SINGLE_ASSET A5 | B13: ='Period 1'!I14 | C13: =0 | D13: =Assets!$H$9 | E13: =B13+C13-D13 | F13: =IF(OR(E13<0,TRUE),0,ROUND(E13*Rules!$B$3/100*$B$3,2)) | G13: =IF(AND(TRUE,E13>=0),E13,0) | H13: =IF(E13<0,-E13,0) | I13: =IF(E13<0,0,E13-F13-G13) | J13: 0 | K13: 0 | L13: 220 | M13: 0
A15: Totals | B15: Workings | C15: Expected
A16: AIA | B16: =SUM(C8:C8) | C16: 498630.14
A17: Writing-down allowances | B17: =SUM(F11:F13) | C17: 24369.06
A18: Balancing allowances | B18: =SUM(G11:G13) | C18: 0
A19: Allowances | B19: =B16+B17+B18 | C19: 522999.2
A20: Balancing charges | B20: =SUM(H11:H13) | C20: 220
A22: Check: workings equal expected | B22: =AND(ROUND(B16-C16,2)=0,ROUND(B17-C17,2)=0,ROUND(B18-C18,2)=0,ROUND(B19-C19,2)=0,ROUND(B20-C20,2)=0,ROUND(B4-C4,2)=0,ROUND(C8-E8,2)=0,ROUND(F11-J11,2)=0,ROUND(G11-K11,2)=0,ROUND(H11-L11,2)=0,ROUND(I11-M11,2)=0,ROUND(F12-J12,2)=0,ROUND(G12-K12,2)=0,ROUND(H12-L12,2)=0,ROUND(I12-M12,2)=0,ROUND(F13-J13,2)=0,ROUND(G13-K13,2)=0,ROUND(H13-L13,2)=0,ROUND(I13-M13,2)=0)
