Workbook

Sheet About
A1: V4-M4 golden workings: losses, tax by financial year and marginal relief (DEC-101)
A3: V4-M4 (DEC-101) golden: a profitable 12-month CT period across two financial years (2027), then a 182-day loss period (January to June 2028) whose loss is carried back to it. The rates and limits (main 25%, small profits 19%, limits £50,000 and £250,000, fraction 3/200) are fixtures entered and verified in the test, not tax advice. Worked by hand in docs/architecture/v4-m4-golden-workings.xlsx.
A4: Trading profit = adjusted profit - capital allowances + balancing charges. Taxable total profits = trading profit - losses brought forward used - loss carried back from the next period.
A5: Profits are apportioned to financial years by days (first part rounded to the penny, the last part the remainder).
A6: Limits per part = annual limit x days of the part / (days of the period if 12 months, else 365) / (1 + associated companies), rounded to the penny.
A7: At or under the lower limit: small profits rate; at or over the upper: main rate; between: main rate less fraction x (upper limit - profits).
A8: Green cells are the golden the tests assert; each sheet's Check row must be TRUE.

Sheet Rates
A1: Main rate % | B1: 25
A2: Small profits rate % | B2: 19
A3: Lower limit | B3: 50000
A4: Upper limit | B4: 250000
A5: Marginal relief fraction | B5: 0.015

Sheet A before carry back
A1: A before carry back
A2: Days in the period | B2: 365
A3: Limits divide by | B3: =B2
A4: Associated companies | B4: 0
A6: Sales (4000) | B6: 200000
A7: Wages (6000) | B7: -50000
A8: Adjusted profit | B8: =B6+B7 | C8: 150000
A9: Main pool opening | B9: 111111.11
A10: Capital allowances (WDA 18%) | B10: =ROUND(B9*18/100,2) | C10: 20000
A11: Trading profit | B11: =MAX(B8-B10,0) | C11: 130000
A12: Losses brought forward | B12: 10000
A13: Losses brought forward used | B13: =MIN(B12,B11) | C13: 10000
A14: Loss carried back from B | B14: 0
A15: Taxable total profits | B15: =B11-B13-B14 | C15: 120000
A17: Financial year | B17: Days | C17: Profit | D17: Lower limit | E17: Upper limit | F17: Tax at rate | G17: Marginal relief | H17: Tax | I17: Expected tax | J17: Expected relief
A18: 2026 | B18: 90 | C18: =ROUND(B15*B18/$B$2,2) | D18: =ROUND(Rates!$B$3*B18/$B$3/(1+$B$4),2) | E18: =ROUND(Rates!$B$4*B18/$B$3/(1+$B$4),2) | F18: =IF(C18<=D18,ROUND(C18*Rates!$B$2/100,2),ROUND(C18*Rates!$B$1/100,2)) | G18: =IF(AND(C18>D18,C18<E18),ROUND(Rates!$B$5*(E18-C18),2),0) | H18: =F18-G18 | I18: 6916.44 | J18: 480.82
A19: 2027 | B19: 275 | C19: =B15-SUM(C18:C18) | D19: =ROUND(Rates!$B$3*B19/$B$3/(1+$B$4),2) | E19: =ROUND(Rates!$B$4*B19/$B$3/(1+$B$4),2) | F19: =IF(C19<=D19,ROUND(C19*Rates!$B$2/100,2),ROUND(C19*Rates!$B$1/100,2)) | G19: =IF(AND(C19>D19,C19<E19),ROUND(Rates!$B$5*(E19-C19),2),0) | H19: =F19-G19 | I19: 21133.56 | J19: 1469.18
A20: Corporation tax | H20: =SUM(H18:H19) | I20: 28050
A22: Check: workings equal expected | B22: =AND(ROUND(B8-C8,2)=0,ROUND(B10-C10,2)=0,ROUND(B11-C11,2)=0,ROUND(B13-C13,2)=0,ROUND(B15-C15,2)=0,ROUND(H18-I18,2)=0,ROUND(G18-J18,2)=0,ROUND(C18-29589.04,2)=0,ROUND(H19-I19,2)=0,ROUND(G19-J19,2)=0,ROUND(C19-90410.96,2)=0,ROUND(H20-I20,2)=0)

Sheet B loss period
A1: B loss period
A2: Days in the period | B2: 182
A3: Limits divide by | B3: 365
A4: Associated companies | B4: 0
A6: Sales (4000) | B6: 10000
A7: Wages (6000) | B7: -40000
A8: Adjusted profit | B8: =B6+B7 | C8: -30000
A9: Main pool from A (closing) | B9: 91111.11
A10: Capital allowances (18% x 182/365) | B10: =ROUND(B9*18/100*182/365,2) | C10: 8177.53
A11: Trading loss | B11: =MAX(B10-B8,0) | C11: 38177.53
A12: Carried back to A (claim) | B12: =B11 | C12: 38177.53
A13: Losses carried forward | B13: =B11-B12 | C13: 0
A14: Taxable total profits | B14: 0 | C14: 0
A16: Financial year | B16: Days | C16: Profit | D16: Lower limit | E16: Upper limit | F16: Tax at rate | G16: Marginal relief | H16: Tax | I16: Expected tax | J16: Expected relief
A17: 2027 | B17: 91 | C17: =ROUND(B14*B17/$B$2,2) | D17: =ROUND(Rates!$B$3*B17/$B$3/(1+$B$4),2) | E17: =ROUND(Rates!$B$4*B17/$B$3/(1+$B$4),2) | F17: =IF(C17<=D17,ROUND(C17*Rates!$B$2/100,2),ROUND(C17*Rates!$B$1/100,2)) | G17: =IF(AND(C17>D17,C17<E17),ROUND(Rates!$B$5*(E17-C17),2),0) | H17: =F17-G17 | I17: 0 | J17: 0
A18: 2028 | B18: 91 | C18: =B14-SUM(C17:C17) | D18: =ROUND(Rates!$B$3*B18/$B$3/(1+$B$4),2) | E18: =ROUND(Rates!$B$4*B18/$B$3/(1+$B$4),2) | F18: =IF(C18<=D18,ROUND(C18*Rates!$B$2/100,2),ROUND(C18*Rates!$B$1/100,2)) | G18: =IF(AND(C18>D18,C18<E18),ROUND(Rates!$B$5*(E18-C18),2),0) | H18: =F18-G18 | I18: 0 | J18: 0
A19: Corporation tax | H19: =SUM(H17:H18) | I19: 0
A21: Check: workings equal expected | B21: =AND(ROUND(B8-C8,2)=0,ROUND(B10-C10,2)=0,ROUND(B11-C11,2)=0,ROUND(B12-C12,2)=0,ROUND(B13-C13,2)=0,ROUND(B14-C14,2)=0,ROUND(H17-I17,2)=0,ROUND(G17-J17,2)=0,ROUND(C17-0.0,2)=0,ROUND(H18-I18,2)=0,ROUND(G18-J18,2)=0,ROUND(C18-0.0,2)=0,ROUND(H19-I19,2)=0)

Sheet A after carry back
A1: A after carry back
A2: Days in the period | B2: 365
A3: Limits divide by | B3: =B2
A4: Associated companies | B4: 0
A6: Sales (4000) | B6: 200000
A7: Wages (6000) | B7: -50000
A8: Adjusted profit | B8: =B6+B7
A9: Main pool opening | B9: 111111.11
A10: Capital allowances (WDA 18%) | B10: =ROUND(B9*18/100,2)
A11: Trading profit | B11: =MAX(B8-B10,0)
A12: Losses brought forward | B12: 10000
A13: Losses brought forward used | B13: =MIN(B12,B11)
A14: Loss carried back from B | B14: ='B loss period'!B12 | C14: 38177.53
A15: Taxable total profits | B15: =B11-B13-B14 | C15: 81822.47
A17: Financial year | B17: Days | C17: Profit | D17: Lower limit | E17: Upper limit | F17: Tax at rate | G17: Marginal relief | H17: Tax | I17: Expected tax | J17: Expected relief
A18: 2026 | B18: 90 | C18: =ROUND(B15*B18/$B$2,2) | D18: =ROUND(Rates!$B$3*B18/$B$3/(1+$B$4),2) | E18: =ROUND(Rates!$B$4*B18/$B$3/(1+$B$4),2) | F18: =IF(C18<=D18,ROUND(C18*Rates!$B$2/100,2),ROUND(C18*Rates!$B$1/100,2)) | G18: =IF(AND(C18>D18,C18<E18),ROUND(Rates!$B$5*(E18-C18),2),0) | H18: =F18-G18 | I18: 4421.82 | J18: 622.03
A19: 2027 | B19: 275 | C19: =B15-SUM(C18:C18) | D19: =ROUND(Rates!$B$3*B19/$B$3/(1+$B$4),2) | E19: =ROUND(Rates!$B$4*B19/$B$3/(1+$B$4),2) | F19: =IF(C19<=D19,ROUND(C19*Rates!$B$2/100,2),ROUND(C19*Rates!$B$1/100,2)) | G19: =IF(AND(C19>D19,C19<E19),ROUND(Rates!$B$5*(E19-C19),2),0) | H19: =F19-G19 | I19: 13511.13 | J19: 1900.64
A20: Corporation tax | H20: =SUM(H18:H19) | I20: 17932.95
A22: Check: workings equal expected | B22: =AND(ROUND(B14-C14,2)=0,ROUND(B15-C15,2)=0,ROUND(H18-I18,2)=0,ROUND(G18-J18,2)=0,ROUND(C18-20175.4,2)=0,ROUND(H19-I19,2)=0,ROUND(G19-J19,2)=0,ROUND(C19-61647.07,2)=0,ROUND(H20-I20,2)=0)
