Workbook

Sheet About
A1: V5-M1 golden workings: the VAT return of a synthetic quarter (DEC-090)
A3: Period | B3: 2026-01-01 to 2026-03-31 (quarters ending March, June, September, December)
A4: Source | B4: tests/api/vat-return.test.ts; the platform's figures are in the 'Expected' column of 'Boxes'
A5: Status | B5: FOR REVIEW by the named accountant (DEC-054 pattern). Not a real return; nothing is filed (DEC-082, DEC-086)
A6: Rates | B6: SYNTHETIC: 20% on the test codes SX (sales: net box 6, VAT box 1) and PX (purchases: net box 7, VAT box 4), entered by one person and verified by another in the test
A7: Yellow cells | B7: Inputs (the journal lines)
A8: Green cells | B8: What the platform returned in the test
A9: What to check | B9: That each box equals the formula over the lines; that the reconciliation difference is the late sale's VAT; that both flags are raised for the reason given

Sheet Lines
A1: Journal | B1: Journal date | C1: Tax point | D1: Description | E1: Account | F1: VAT code | G1: Side | H1: Net | I1: Rate % | J1: VAT | K1: Net box | L1: VAT box | M1: Tax point in period | N1: Journal date in period
A2: J1 | B2: 2026-02-10 | C2: 2026-02-10 | D2: Synthetic sale | E2: 4000 Sales | F2: SX | G2: SALES | H2: 1000 | I2: 20 | J2: =ROUND(H2*I2/100,2) | K2: 6 | L2: 1 | M2: =AND(C2>="2026-01-01",C2<="2026-03-31") | N2: =AND(B2>="2026-01-01",B2<="2026-03-31")
A3: J2 | B3: 2026-02-20 | C3: 2026-02-20 | D3: Synthetic purchase | E3: 6310 Expenses | F3: PX | G3: PURCHASES | H3: 400 | I3: 20 | J3: =ROUND(H3*I3/100,2) | K3: 7 | L3: 4 | M3: =AND(C3>="2026-01-01",C3<="2026-03-31") | N3: =AND(B3>="2026-01-01",B3<="2026-03-31")
A4: J3 | B4: 2026-04-05 | C4: 2026-03-30 | D4: Synthetic sale entered after the period | E4: 4000 Sales | F4: SX | G4: SALES | H4: 100 | I4: 20 | J4: =ROUND(H4*I4/100,2) | K4: 6 | L4: 1 | M4: =AND(C4>="2026-01-01",C4<="2026-03-31") | N4: =AND(B4>="2026-01-01",B4<="2026-03-31")

Sheet Boxes
A1: Box | B1: What it holds | C1: Working | D1: Amount | E1: Expected (platform) | F1: Agrees
A2: 1 | B2: VAT due on sales | C2: SUM of VAT on lines whose VAT box is 1 and tax point is in the period | D2: =SUMIFS(Lines!J$2:J$4,Lines!L$2:L$4,"1",Lines!M$2:M$4,TRUE) | E2: 220 | F2: =ROUND(D2-E2,2)=0
A3: 2 | B3: VAT due on acquisitions from the EU | C3: No line maps to box 2 | D3: =0 | E3: 0 | F3: =ROUND(D3-E3,2)=0
A4: 3 | B4: Total VAT due (box 1 + box 2) | C4: Box 1 + box 2 | D4: =D2+D3 | E4: 220 | F4: =ROUND(D4-E4,2)=0
A5: 4 | B5: VAT reclaimed on purchases | C5: SUM of VAT on lines whose VAT box is 4 and tax point is in the period | D5: =SUMIFS(Lines!J$2:J$4,Lines!L$2:L$4,"4",Lines!M$2:M$4,TRUE) | E5: 80 | F5: =ROUND(D5-E5,2)=0
A6: 5 | B6: Net VAT to pay (or reclaim) | C6: Box 3 - box 4; payable because box 3 is larger | D6: =ABS(D4-D5) | E6: 140 | F6: =ROUND(D6-E6,2)=0
A7: 6 | B7: Total sales excluding VAT | C7: SUM of net on lines whose net box is 6 and tax point is in the period (exact; whole pounds are V5-M2) | D7: =SUMIFS(Lines!H$2:H$4,Lines!K$2:K$4,"6",Lines!M$2:M$4,TRUE) | E7: 1100 | F7: =ROUND(D7-E7,2)=0
A8: 7 | B8: Total purchases excluding VAT | C8: SUM of net on lines whose net box is 7 and tax point is in the period | D8: =SUMIFS(Lines!H$2:H$4,Lines!K$2:K$4,"7",Lines!M$2:M$4,TRUE) | E8: 400 | F8: =ROUND(D8-E8,2)=0
A9: 8 | B9: Supplies to the EU | C9: No line maps to box 8 | D9: =0 | E9: 0 | F9: =ROUND(D9-E9,2)=0
A10: 9 | B10: Acquisitions from the EU | C10: No line maps to box 9 | D10: =0 | E10: 0 | F10: =ROUND(D10-E10,2)=0

Sheet Reconciliation
A1: Item | B1: Working | C1: Amount | D1: Expected (platform) | E1: Agrees
A2: Movement on the VAT accounts by journal date | B2: SUMIFS of VAT (credit-positive: sales +, purchases -) on lines dated in the period | C2: =SUMIFS(Lines!J$2:J$4,Lines!G$2:G$4,"SALES",Lines!N$2:N$4,TRUE)-SUMIFS(Lines!J$2:J$4,Lines!G$2:G$4,"PURCHASES",Lines!N$2:N$4,TRUE) | D2: 120 | E2: =ROUND(C2-D2,2)=0
A3: VAT lines by tax point | B3: The same, on lines whose tax point is in the period | C3: =SUMIFS(Lines!J$2:J$4,Lines!G$2:G$4,"SALES",Lines!M$2:M$4,TRUE)-SUMIFS(Lines!J$2:J$4,Lines!G$2:G$4,"PURCHASES",Lines!M$2:M$4,TRUE) | D3: 140 | E3: =ROUND(C3-D3,2)=0
A4: Difference | B4: Movement - VAT lines: the VAT of J3, dated after the period with a tax point inside it | C4: =C2-C3 | D4: -20 | E4: =ROUND(C4-D4,2)=0

Sheet Flags
A1: Flag key | B1: Raised? | C1: Why | D1: Explained in the test as
A2: reconciliation_difference | B2: Yes | C2: The difference on 'Reconciliation' is not zero (-20.00) | D2: The sale was invoiced in March and entered in April (synthetic)
A3: late_posting:{J3}:{VAT line} | B3: Yes | C3: J3 is dated 2026-04-05, after the period, with a tax point (2026-03-30) inside it | D3: The sale was invoiced in March and entered in April (synthetic)
A4: superseded_rate:{rateId} | B4: No | C4: Neither rate version has been superseded
A5: repayment | B5: No | C5: Box 4 (80.00) is not more than boxes 1 and 2 (220.00)
A6: zero_return | B6: No | C6: Boxes are not all zero

Sheet Steps
A1: Step | B1: Who (test role) | C1: Result in the platform
A2: Open the return (date 2026-02-15) | B2: Accountant (vat:prepare) | C2: Period 2026-01-01 to 2026-03-31; linked to the VAT obligation; DRAFT
A3: Prepare | B3: Accountant | C3: PREPARED on the fingerprint of J1 and J2
A4: Post J3 (dated 5 April, tax point 30 March) | B4: Accountant | C4: Fingerprint changes; the preparation lapses (DRAFT); two flags raised
A5: Prepare again; explain both flags | B5: Accountant | C5: PREPARED; no unexplained flag
A6: Review | B6: Partner (vat:review), not the preparer | C6: REVIEWED
A7: Client approval (2026-04-20, director contact, signed approval scanned clean) | B7: Partner (vat:review and period:lock) | C7: APPROVED; return frozen; period locked; obligation READY
A8: Post a sale with tax point 2026-03-15 | B8: Accountant | C8: Refused: vat_period_locked

Sheet Sign-off
A1: Reviewer | B1: Date | C1: Agrees (yes/no) | D1: Notes
